{
  "feature_cols": [
    "N",
    "P",
    "K",
    "temperature",
    "humidity",
    "ph",
    "rainfall",
    "npk_sum",
    "npk_balance",
    "n_to_p_ratio",
    "p_to_k_ratio",
    "n_to_k_ratio",
    "ph_acidic",
    "ph_alkaline",
    "ph_neutral",
    "temp_category",
    "rainfall_category",
    "humidity_category",
    "n_deficient",
    "p_deficient",
    "k_deficient",
    "crop_encoded"
  ],
  "fertilizers": [
    "10:10:10 Npk",
    "10:26:26 Npk",
    "12:32:16 Npk",
    "13:32:26 Npk",
    "18:46:00 Npk",
    "19:19:19 Npk",
    "20:20:20 Npk",
    "50:26:26 Npk",
    "Ammonium Sulphate",
    "Chilated Micronutrient",
    "Compost",
    "Dap",
    "Ferrous Sulphate",
    "Hydrated Lime",
    "Magnesium Sulphate",
    "Mop",
    "Npk",
    "Ssp",
    "Sulphur",
    "Urea",
    "White Potash",
    "Zinc Sulphate"
  ],
  "crops": [
    "Cotton",
    "Ginger",
    "Gram",
    "Grapes",
    "Groundnut",
    "Jowar",
    "Maize",
    "Masoor",
    "Moong",
    "Potato",
    "Rice",
    "Soybean",
    "Sugarcane",
    "Tomato",
    "Tur",
    "Turmeric",
    "Urad",
    "Wheat"
  ],
  "temp_categories": [
    "cold",
    "hot",
    "moderate",
    "warm"
  ],
  "rainfall_categories": [
    "high",
    "low",
    "medium",
    "very_high"
  ],
  "humidity_categories": [
    "high",
    "low",
    "moderate",
    "very_high"
  ]
}